[{"categories":null,"content":"Des députés invisibles Comme beaucoup, j’ai été interpellé par les scènes de tensions qui ont accompagné la seance de la rentrée parlementaire au Sénégal du 12 septembre 2022. Mais derrière les violences et les insultes déplorables, ce qui m’interpelle le plus quand on évoque l’assemblée nationale, c’est le peu d’informations en ligne que l’on dispose sur les députés. On trouve beaucoup de chiffres officiels, des listes de partis ou de coalitions; des pourcentages sur le scrutin, sur le genre. Et les sites d’informations locaux fournissent le compte-rendu régulier et précis des travaux de l’hémycicle, mais aucun ne prend le temps de travailler sur des profils, des parcours, des contextes idéologiques voire même des photos. Le site officiel de l’Assemblée Nationale propose quelques données exploitables sur l’actuelle législature. Mais, à part ça, si on veut en savoir plus sur les personnes qui sont en charge des préocupations quotidiennes du peuple, il va falloir se fier à son imagination. C’est pourquoi j’ai décidé d’entamer une série d’articles accompagnés de visuels interactifs sur l’assemblée nationale du Sénégal. Sa répartition en sièges, les députés, mais également l’historique, la composition des commissions, des bureaux, le vote des lois etc. En gros, tout ce qui sera possible de collecter en donnnées et de convertir en graphiques. En guise d’introduction à ce travail par étapes, je me contenterai d’utiliser les données récupérées sur le site de l’assemblée et de visualiser les chiffres officiels concernant la répartition des sièges par coalition, par genre, ainsi qu’une carte et de la représentation des députés et des départements qu’ils représentent. Pour cette fois, j’utilise Flourish pour les graphiques mais à l’avenir je ne m’interdirais pas d’utiliser d’autres applications ou librairies. data sources and tools used Sources de données National Assembly emedia.sn wikipedia Inter-Parliamentary Union App, plug-in Flourish Bamboolib web scraper Python ","date":"2022-09-22","objectID":"/fr/senegal-parlement-chroniques/:1:0","tags":["Datavisualisation","Flourish","Storytelling"],"title":"Rencontre ton député","uri":"/fr/senegal-parlement-chroniques/"},{"categories":["Dataviz"],"content":"Un article sur le Story-Telling en Python\"","date":"2022-08-03","objectID":"/fr/mon-post-interlangue/","tags":["Jupyter Notebook"," Plotly","DataPane","MonkeyPox","Python"],"title":"Visualiser la 'Variole du singe' avec DataPane # Partie I ","uri":"/fr/mon-post-interlangue/"},{"categories":["Dataviz"],"content":"Visualiser avec python c’est bien mais… Au départ, Il s’agissait juste d’écrire un article sur l’épidémie de la Variole du Singe illustré de quelques visualisations réalisées avec la librairie graphique Python, Plotly. Mais quand il a fallu intégrer mes graphiques interactifs à mon article, j’ai rencontré tout un tas de problèmes. Des problèmes de droits d’accès ou de dépassement de taille avec studiolab. Des problèmes pratiques, de responsivité en utilisant les méthodes d’hébergement alternatives. Je savais que les librairies graphiques Python étaient aussi robustes et efficaces que difficiles à intégrer et à partager. Mais là j’étais à deux doigts de jeter l’éponge et de me tourner vers des solutions Java Script “prêtes à visualiser” du type Flourish ou Datawarper. Et puis je me suis souvenu de DataPane. C’est une librairie que j’avais déjà utilisé pour intégrer des visualisations. A l’époque, elle ne m’avait pas laissé un souvenir très marquant. Mais dans la situation actuelle, j’ai jugé bon d’y regarder de plus près. Datapane c’est à la fois une librairie Python qui permet de créer des rapports interactifs et une plateforme [Open] qui permet de les stocker, de les partager via et sur de nombreux supports. On peut y intégrer directement des objets python, qu’il s’agisse de texte markdown, des graphiques - Plotly, Altair, Bokeh, Matplotlib etc. -, de html, de tables ou des médias. A mon sens, Datapane est un outil particulièrement attractif pour plusieurs raisons D’abord les rapports peuvent être programmés directement à partir d’un environnement local et unique (Jupyter Notebook, Colab, Airflow etc.). Ensuite, la flexibilité de la structure et la simplicité de la syntaxe laissent une grande place à l’intuition. Et permettent à Datapane de répondre à de nombreux besoins. On peut aussi bien utiliser DataPane pour partager une simple visualisation programmée sur Notebook, pour créer un tableau de bord ou pour réaliser et déployer une application complexe. Enfin, la facilité pour partager ou pour intégrer les rapports sur des pages web sur des applications communautaires du type Slack ou discord. Du coup, plutôt que de faire un simple article qui intégrerait quelques visualisations, j’ai décidé de faire un rapport interactif de plusieurs pages. La variole du singe ou MonkeyPox qui se propage actuellement dans le monde de façon m’a semblé être un sujet intéressant. D’abord, c’est une actualité sanitaire qui nous concerne tous. Ensuite, les données étant régulièrement actualisées, nous pourrons créer un rapport interactif régulièrement mis à jour. Sur les données utilisées Les données proviennent de l’association GlobalHealth qui suit l’évolution de la propagation de la maladie depuis l’apparition des premiers cas. A des fins personnelles j’y ai ajouté quelques variables, \"Continents\", \"SubRegion\", les coordonnées géographiques, \"latitude\", \"longitude\" et les décès, deaths. (lien du fichier) ","date":"2022-08-03","objectID":"/fr/mon-post-interlangue/:1:0","tags":["Jupyter Notebook"," Plotly","DataPane","MonkeyPox","Python"],"title":"Visualiser la 'Variole du singe' avec DataPane # Partie I ","uri":"/fr/mon-post-interlangue/"},{"categories":["Dataviz"],"content":"Le détail du travail Nous allons faire un rapport de quatre pages : 1 page d’accueil qui contiendra du texte markdown et affichera les principales statistiques 1 page de charts avec différents graphiques interactifs et comparatifs 1 page pour la carte 1 page de tables Cette première pratique sera essentiellement consacrée à la page d’introduction. Ce qui nous permettra également de présenter la structure générale de DataPane que nous rencontrerons tout au long de la programmation du rapport. MonkeyPox DataExplorer IFrame not supported ","date":"2022-08-03","objectID":"/fr/mon-post-interlangue/:2:0","tags":["Jupyter Notebook"," Plotly","DataPane","MonkeyPox","Python"],"title":"Visualiser la 'Variole du singe' avec DataPane # Partie I ","uri":"/fr/mon-post-interlangue/"},{"categories":["Dataviz"],"content":"Installation et datas si ce n’est pas déjà fait la première chose est d’installer Datapane et de l’importer pip3 install datapane et de l’importer avec les librairies dont nous aurons besoin import pandas as pd import datapane as dp import plotly.graph_objs as go import plotly.express as px df = pd.read_csv('newmonkeyset.csv') df ⤵️ Lire le dataframe avec DataTable de Datapane Le dataset est une timeserie des cas de MonkeyPox déclarés depuis le mois de janvier 2002 jusqu’à présent. Bien que l’on ait recommencé à évoquer la maladie à l’apparition des premiers cas en Europe, il inclût également les cas déclarés antérieurement en Afrique dans les pays où la maladie est endémique. En passant notre jeu de données dans le bloc DataTable nous pouvons déjà charger et partager un premier Report. Ce qui permettra à notre interlocuteur ou aux lecteurs, de l’explorer, de l’ordonner, de créer des filtres conditionels, de faire des requêtes SQL et de l’importer dans différents formats. Nous pouvons également utiliser le bloc Table si nous souhaitons simplement afficher quelques données filtrées. Pour notre box, nous utiliserons les deux. #Let's try to load a DataTable table = dp.DataTable(df) report = dp.Report(table) report.upload(name=\"datapox\") IFrame not supported ","date":"2022-08-03","objectID":"/fr/mon-post-interlangue/:3:0","tags":["Jupyter Notebook"," Plotly","DataPane","MonkeyPox","Python"],"title":"Visualiser la 'Variole du singe' avec DataPane # Partie I ","uri":"/fr/mon-post-interlangue/"},{"categories":["Dataviz"],"content":"Page d’Accueil Dans Datapane les rapports sont composés de plusieurs blocs, qui englobent des objets Python, comme nous l’avons signalé plus haut. Ces blocs - de texte ou de données - peuvent être eux mêmes englobés dans d’autres blocs de mise en page. La première page est composée d’une liste de 3 éléments blocs : 1 bannière que nous passerons dans le bloc Html 1 bloc texte de présentation au format markdown dans lequel nous passerons les variables de données statistiques 1 groupe de 3 cartes BigNumber pour mettre en évidence les données principales de l’épidémie Le tout englobé dans des blocs de mise en page, dp.Group(), calés sur 2 colonnes. Ce qui nous donnera la structure de base suivante : dp.Report( dp.Page(title = 'intro', blocks = [ dp.HTML(),#html banner image dp.Group( dp.Group( #text title dp.text()# full markdown text ), dp.Group( dp.BigNumber(),#Global cases + indicators dp.BigNumber(),# Deaths dp.BigNumber(),#Countries affected number dp.BigNumber()#Last entries Country ), columns = 2) ] ), dp.Page(title = 'Monkey Pox in Charts'), dp.Page(title = 'Animated Map'), dp.Page(title = 'data') ) Mais avant de nous intéresser à la structure du rapport, nous devons créer nos objets et préparer nos données. La bannière Pour la bannière, c’est bien simple, on créé une variable html_banner avec du html que l’on va passer dans le bloc dp.Html() 🐵 html_banner = \"\"\"\u003cdiv style=\"padding: 10px;display: flex;align-items: center;font-size: 40px;color: #312E81;background: #EEF2FF;\"\u003e \u003cimg src=\"https://axtell.com/wp-content/uploads/2020/06/monkey34.jpg\" style=\"margin-right: 1em; max-height: 250px;\"\u003e \u003ch1\u003eMonkyPox Data Explorer\u003c/h1\u003e \u003c/div\u003e \"\"\" Texte Intro On peut utiliser du markdown pour le passer dans le bloc text dp.Text(). Ici, j’ai souhaité que notre texte de présentation contienne des données actualisées en temps réel. Par ex: le nombre total de cas, le pays le plus affecté, la moyenne des contaminations par jour etc. # Set the variables to be included to entry text df['date_time'] = pd.to_datetime(df['date'], format ='%Y-%m-%d') #average number of cases per day since the first European cases df_NE = df.loc[df['date_time'] \u003e '2022-05-01'] daily_mean = df_NE.groupby('date')['daily_cases'].sum().reset_index() daymean = round(daily_mean.daily_cases.mean(), 2) # Most affected country name \u0026 cases Nb first_country_name = df.groupby('Country')['cumulative_cases'].max().sort_values(ascending = False).reset_index()['Country'][0] first_country_nb_cases = df.groupby('Country')['cumulative_cases'].max().sort_values(ascending = False).reset_index()['cumulative_cases'][0] first_country_nb_cases = '{:,}'.format(first_country_nb_cases) #Nb Deaths deaths = df.groupby('date')['cumulative_deaths'].sum().iloc[-1] #10 most affected countries global cases \u0026 percent top_ten = df.groupby('Country')['cumulative_cases'].max().reset_index().sort_values(by=['cumulative_cases'], ascending = False).head(10) topten_global = top_ten['cumulative_cases'].sum() topten_global = '{:,}'.format(topten_global) topten_percent = round(top_ten['cumulative_cases'].sum()/df['daily_cases'].sum()*100, 2) # liste_countries = ['Greenland', 'Honduras', 'Moldova', 'Monaco','Andorra', 'Argentina', 'Australia', 'Austria', 'Barbados', 'Belgium', 'Benin', 'Bermuda', 'Bolivia', 'Bosnia', 'Brazil', 'Bulgaria', 'Cameroon', 'Canada', 'Central African Republic', 'Chile', 'China', 'Colombia', 'Congo', 'Costa Rica', 'Croatia', 'Cyprus', 'Czech Republic', 'Democratic Republic of Congo', 'Denmark', 'Dominican Republic', 'Ecuador', 'Estonia', 'Finland', 'France', 'Georgia', 'Germany', 'Ghana', 'Gibraltar', 'Greece', 'Guadeloupe', 'Guatemala', 'Hungary', 'Iceland', 'India', 'Ireland', 'Israel', 'Italy', 'Jamaica', 'Japan', 'Latvia', 'Lebanon', 'Liberia','Saint Martin (French part)', 'Lithuania', 'Luxembourg', 'Malta', 'Martinique', 'Mexico', 'Montenegro', 'Morocco', 'Netherlands', 'New Caledonia', 'New Zealand', 'Nigeria', 'Norway', 'Panama', 'Peru', 'Philippines', 'Poland', 'Portugal', 'Puerto","date":"2022-08-03","objectID":"/fr/mon-post-interlangue/:3:1","tags":["Jupyter Notebook"," Plotly","DataPane","MonkeyPox","Python"],"title":"Visualiser la 'Variole du singe' avec DataPane # Partie I ","uri":"/fr/mon-post-interlangue/"},{"categories":["Dataviz"],"content":"Cartes BigNumber …Et les valeurs des blocks BigNumber #Bignumber data global_cases = df.groupby('date')['cumulative_cases'].sum().iloc[-1] global_cases_change = df.groupby('date')['cumulative_cases'].sum().iloc[-1] - df.groupby('date')['cumulative_cases'].sum().iloc[-2] nb_countries = len(df['Country'].unique()) nb_deaths = df['deaths'].sum() ###### Report ###### dp.Report( dp.Page( title = \"Intro\", blocks = [ dp.HTML(banner_html), dp.Group( dp.Group( '## resume', dp.Text(md), ), dp.Group( dp.BigNumber( heading = 'GLOBAL CASES', value='{:,}'.global_cases, change ='{:,}'.global_cases_change), is_upward_change=True, ), dp.BigNumber( heading = 'NUMBER OF COUNTRIES', value = len(data_world['Country'].unique()), dp.BigNumber( heading = 'DEATHS', value = nb_deaths) ), columns =2) ] ), dp.Page(title = 'Monkey Pox in Charts'), dp.Page(title = 'Animated Map'), dp.Page(title = 'data') ) ","date":"2022-08-03","objectID":"/fr/mon-post-interlangue/:3:2","tags":["Jupyter Notebook"," Plotly","DataPane","MonkeyPox","Python"],"title":"Visualiser la 'Variole du singe' avec DataPane # Partie I ","uri":"/fr/mon-post-interlangue/"},{"categories":null,"content":"Graphiques animées","date":"2022-10-26","objectID":"/fr/f1championnatgraphique/","tags":["dataviz, Flourish"],"title":"Championnat de F1 2022: les dernières batailles en Graphiques interactifs","uri":"/fr/f1championnatgraphique/"},{"categories":null,"content":" Charles Leclerc (Ferrari) contre Siergo Perez (Red Bull) pour la seconode place pilotes. Georges Russell (Mercedes) contre Carlos Sainz (Ferrari) pour la 4ème place avec Hamilton (Mercedes), en forme et en embuscade, pour tenter de souffler la seconde place constructeurs à Ferrari. Alpine contre McLaren pour tenter d’être le meilleur des “autres”. Voici en trois graphiques animés et interactifs quelques-uns des enjeux de la fin de saison de Formule 1 2022 ","date":"2022-10-26","objectID":"/fr/f1championnatgraphique/:0:0","tags":["dataviz, Flourish"],"title":"Championnat de F1 2022: les dernières batailles en Graphiques interactifs","uri":"/fr/f1championnatgraphique/"},{"categories":null,"content":"Charles Leclerc VS Sergio Perez Charles Leclerc, Ferrari et Sergio Perez, Red Bull Racing, lors du Grand Prix de Suzuka 2022. Motorsport Images Prétendant au titre en début de saison Charles Leclerc occupait confortablement la tête du championnat après les premiers grands prix. Mais handicapé par les problèmes de fiabilité de la Ferrari, pénalisé par les incohérences stratégiques de sa team et sanctionné par des erreurs de pilotage, il a progressivement vu le titre s’envoler et Sergio Perez le rattraper au classement. Séparés par deux points, les deux pilotes se livrent à un chassé/croisé depuis le grand prix de Monaco. ","date":"2022-10-26","objectID":"/fr/f1championnatgraphique/:0:1","tags":["dataviz, Flourish"],"title":"Championnat de F1 2022: les dernières batailles en Graphiques interactifs","uri":"/fr/f1championnatgraphique/"},{"categories":null,"content":"Russell, Sainz, Hamilton : une lutte à 3 pour la quatrième place La lutte pour la quatrième place du classement pilotes est tout aussi serrée que pour la seconde. Depuis le début de la saison, elle est l'objet d'un chassé-croisé entre Carlos Sainz (Ferrari) et Georges Russell (Mercedes) avec un avantage de 16 points pour le Britannique. Loin d'être anecdotique, cette bataille pourrait être déterminante pour la seconde place constructeurs. Le regain de forme des Mercedes et notammment de Lewis Hamilton, les déboires de Sainz et son zéro pointé sur les deux derniers Grands Prix, ont permit aux flêches d'argent de revenir à 53 points. L'écart est encore conséquent, mais la tendance est clairement du côté Mercedes qui pourrait souffler la seconde place à Ferrari sur le fil. Ce qui était quasi-inimaginable en début de saison. ","date":"2022-10-26","objectID":"/fr/f1championnatgraphique/:0:2","tags":["dataviz, Flourish"],"title":"Championnat de F1 2022: les dernières batailles en Graphiques interactifs","uri":"/fr/f1championnatgraphique/"},{"categories":null,"content":"Alpine Vs Mc Laren : la bataille pour le meilleur des “autres” Fernando Alonzo et Lando Norris lors du grand prix de France 2022 La attendue rivalité entre Alpine et McLaren pour la quatrième place constructeurs a bien eu lieu. Ponctuée par des problèmes de fiabilité depuis le début de la saison, elle semble tourner à l’avantage d’Alpine qui peut s’appuyer sur une monoplace en nette progression et 2 pilotes motivés. A l’opposé McLaren ne peut réellement s’appuyer que sur Lando Norris tant Daniel Ricciardo semble avoir lâché prise et être déjà passé à autre chose. ","date":"2022-10-26","objectID":"/fr/f1championnatgraphique/:0:3","tags":["dataviz, Flourish"],"title":"Championnat de F1 2022: les dernières batailles en Graphiques interactifs","uri":"/fr/f1championnatgraphique/"},{"categories":null,"content":"I - Tableau de bord Covid-19 A propos du tableau de bord Ce tableau de bord intercatif a été réalisé en 2021 pendant la Pandémie de Covid 19. Il a été réalisé Dash et Plotly. Le code est inspiré d’un cours suivi sur Udemy. Les données proviennent du Repo du Centre pour la science et l’ingénierie des systèmes (CSSE) de l’université Johns Hopkins Il détaille : la totalité des cas sur le continent africain la totalité des décès les cas enregistrés les 30 derniers jours Une carte pour géo localiser chaque pays Il est actualisé en même temps que la source des données et déployer sur Heroku avec Dash-tools ","date":"2022-10-16","objectID":"/fr/projet/:0:1","tags":null,"title":"Projets","uri":"/fr/projet/"},{"categories":null,"content":"Visualiser les femmes ayant occupé le poste de 1er ministre en 1 graphique","date":"2022-09-26","objectID":"/fr/femmes-premierministre/","tags":["Datataviz","Wikidata","Python"],"title":"Femmes et premier ministre","uri":"/fr/femmes-premierministre/"},{"categories":null,"content":"Femme 1er ministre? rien d’exeptionnel de nos jours Dans quelques jours, il est fort probable que le prochain premier ministre d’Italie soit une première ministre. Comme en Angletterre, le 4 septembre dernier et en France il y a 4 mois, une femme sera à la tête d’une Nation majeure de l’Europe occidentale. Il ne s’agit ici pas de commenter ses choix politiques ou de discourir sur le genre. Car heureusement il n’y a rien d’exeeptionnel à cela de nos jours. Mais cela m’a donné envie de faire un inventaire des femmes ayant occupé cette fonction dans le monde contemporain. De faire des répartitions par âge, par longévité, par continent etc. et de visualiser l’évolution dans le temps. ","date":"2022-09-26","objectID":"/fr/femmes-premierministre/:1:0","tags":["Datataviz","Wikidata","Python"],"title":"Femmes et premier ministre","uri":"/fr/femmes-premierministre/"},{"categories":null,"content":"Récupérer les données avec Wikidata Pour la collecte les données, j’ai choisi d’utiliser Wikidata et de lancer une requête Sparql. A propos de Wikidata et du Sparql Pour rappel, Wikidata est une base de connaissance libre, collaborative et multilingue qui collecte des données structurées pour alimenter Wikipédia et l’ensemble des projets Wikimedia. Tester la requête wikidata : https://w.wiki/5kDx https://observablehq.com/d/99a92633fe5d5149 ","date":"2022-09-26","objectID":"/fr/femmes-premierministre/:2:0","tags":["Datataviz","Wikidata","Python"],"title":"Femmes et premier ministre","uri":"/fr/femmes-premierministre/"},{"categories":null,"content":"A propos de moi ","date":"2022-08-03","objectID":"/fr/about/:0:0","tags":null,"title":"A Propos","uri":"/fr/about/"}]